{
  "date": "",
  "country": "Russia",
  "marketCode": "ru-RU",
  "title": "Info",
  "bsTitle": "",
  "caption": "",
  "copyright": "Eurasian red squirrel (© Galina Jacyna/Getty Images)",
  "copyrightOnly": "",
  "copyrightLink": "/search?q=Eurasian+red+squirrel&form=hpcapt",
  "description": "",
  "quiz": "/search?q=Bing+homepage+quiz&filters=WQOskey:%22HPQuiz_20260121_BerrySquirrel%22&FORM=HPQUIZ",
  "hash": "46c966ca70703e77f48af859efd73280",
  "imageResolutions": [
    {
      "resolution": "Standard",
      "url": "https://www.bing.com/th?id=OHR.BerrySquirrel_ROW7122480645_1366x768.jpg",
      "size": "1366x768"
    },
    {
      "resolution": "FullHD",
      "url": "https://www.bing.com/th?id=OHR.BerrySquirrel_ROW7122480645_1920x1080.jpg",
      "size": "1920x1080"
    },
    {
      "resolution": "HD",
      "url": "https://www.bing.com/th?id=OHR.BerrySquirrel_ROW7122480645_1920x1200.jpg",
      "size": "1920x1200"
    },
    {
      "resolution": "UHD4K",
      "url": "https://www.bing.com/th?id=OHR.BerrySquirrel_ROW7122480645_UHD.jpg",
      "size": "3840x2160"
    }
  ],
  "timeInfo": {
    "startDate": "20260121",
    "fullStartDateTime": "202601210800",
    "endDate": "20260122"
  },
  "createdAt": "202601220300",
  "originalUrlBase": "/th?id=OHR.BerrySquirrel_ROW7122480645"
}