{
  "date": "",
  "country": "Russia",
  "marketCode": "ru-RU",
  "title": "Info",
  "bsTitle": "",
  "caption": "",
  "copyright": "Grand Canyon and the Colorado River, Arizona, United States (© Matt Anderson Photography/Getty Images)",
  "copyrightOnly": "",
  "copyrightLink": "/search?q=Grand+Canyon+National+Park+USA&form=hpcapt",
  "description": "",
  "quiz": "/search?q=Bing+homepage+quiz&filters=WQOskey:%22HPQuiz_20260226_GrandSunset%22&FORM=HPQUIZ",
  "hash": "211399bb2515c0159acd142e6ef9f0ff",
  "imageResolutions": [
    {
      "resolution": "Standard",
      "url": "https://www.bing.com/th?id=OHR.GrandSunset_ROW3515132743_1366x768.jpg",
      "size": "1366x768"
    },
    {
      "resolution": "FullHD",
      "url": "https://www.bing.com/th?id=OHR.GrandSunset_ROW3515132743_1920x1080.jpg",
      "size": "1920x1080"
    },
    {
      "resolution": "HD",
      "url": "https://www.bing.com/th?id=OHR.GrandSunset_ROW3515132743_1920x1200.jpg",
      "size": "1920x1200"
    },
    {
      "resolution": "UHD4K",
      "url": "https://www.bing.com/th?id=OHR.GrandSunset_ROW3515132743_UHD.jpg",
      "size": "3840x2160"
    }
  ],
  "timeInfo": {
    "startDate": "20260226",
    "fullStartDateTime": "202602260800",
    "endDate": "20260227"
  },
  "createdAt": "202602270325",
  "originalUrlBase": "/th?id=OHR.GrandSunset_ROW3515132743"
}