{
  "date": "16. Juni. 2026",
  "country": "Germany",
  "marketCode": "de-DE",
  "title": "Hüter der Korallenriffe",
  "bsTitle": "Hüter der Korallenriffe",
  "caption": "Internationaler Tag der Meeresschildkröten",
  "copyright": "Zwei Echte Karettschildkröten in der Nähe des Seven Mile Beach, Grand Cayman, Kaimaninseln (© Alex Mustard/Nature Picture Library)",
  "copyrightOnly": "© Alex Mustard/Nature Picture Library",
  "copyrightLink": "/search?q=Internationaler+Tag+der+Meeresschildkr%c3%b6ten&form=hpcapt&filters=HpDate%3a%2220260615_2200%22",
  "description": "Seit über 100 Millionen Jahren durchqueren Meeresschildkröten die Ozeane und prägen bis heute empfindliche Meeresökosysteme. Am 16. Juni, dem Internationalen Tag der Meeresschildkröten, rückt ihr Schutz in den Mittelpunkt. Fast alle Arten gelten inzwischen als bedroht, da ihnen Plastikverschmutzung, Klimawandel, Lebensraumverlust und Beifang weltweit zu schaffen machen. Dabei spielen sie eine entscheidende Rolle für das Gleichgewicht der Meere, beispielsweise indem sie Seegraswiesen pflegen, Nährstoffe transportieren und Korallenriffe stabilisieren. Viele Arten legen dabei erstaunliche Distanzen zurück und kehren zur Eiablage an genau jene Strände zurück, an denen sie selbst geschlüpft sind.",
  "quiz": "/search?q=Bing+homepage+quiz&filters=WQOskey:%22HPQuiz_20260615_SevenMileTurtle%22&FORM=HPQUIZ",
  "hash": "5ffc3259a28a83e666a46ba314ef70fd",
  "imageResolutions": [
    {
      "resolution": "Standard",
      "url": "https://www.bing.com/th?id=OHR.SevenMileTurtle_DE-DE3122799407_1366x768.jpg",
      "size": "1366x768"
    },
    {
      "resolution": "FullHD",
      "url": "https://www.bing.com/th?id=OHR.SevenMileTurtle_DE-DE3122799407_1920x1080.jpg",
      "size": "1920x1080"
    },
    {
      "resolution": "HD",
      "url": "https://www.bing.com/th?id=OHR.SevenMileTurtle_DE-DE3122799407_1920x1200.jpg",
      "size": "1920x1200"
    },
    {
      "resolution": "UHD4K",
      "url": "https://www.bing.com/th?id=OHR.SevenMileTurtle_DE-DE3122799407_UHD.jpg",
      "size": "3840x2160"
    }
  ],
  "timeInfo": {
    "startDate": "20260615",
    "fullStartDateTime": "202606152200",
    "endDate": "20260616"
  },
  "createdAt": "202606160625",
  "originalUrlBase": "/th?id=OHR.SevenMileTurtle_DE-DE3122799407"
}