{
  "date": "2025 年 11月 月 18 日",
  "country": "Japan",
  "marketCode": "ja-JP",
  "title": "湖で泳ぐ白黒の冠羽を持つ水鳥",
  "bsTitle": "湖で泳ぐ白黒の冠羽を持つ水鳥",
  "caption": "湖で泳ぐ白黒の冠羽を持つ水鳥",
  "copyright": "オスのオウギアイサ, 米国 オレゴン州 (© Eric Vogt/TANDEM Stills + Motion)",
  "copyrightOnly": "© Eric Vogt/TANDEM Stills + Motion",
  "copyrightLink": "/search?q=%e3%82%aa%e3%82%b9%e3%81%ae%e3%82%aa%e3%82%a6%e3%82%ae%e3%82%a2%e3%82%a4%e3%82%b5&form=hpcapt&filters=HpDate%3a%2220251117_1500%22",
  "description": "今日の画像は米国オレゴン州で撮影したオスのオウギアイサです。カモ科アイサ族に属する水鳥で、カナダ南部から米国の湖沼や湿地に広く生息しています。日本では迷鳥として 1 羽のみ記録があります。体長は約 40～49cm で、頭部に扇状に広がる冠羽が最大の特徴です…",
  "quiz": "/search?q=Bing+homepage+quiz&filters=WQOskey:%22HPQuiz_20251117_AutumnMerganser%22&FORM=HPQUIZ",
  "hash": "52fd709e3a245114700d5b88ac0b8b26",
  "imageResolutions": [
    {
      "resolution": "Standard",
      "url": "https://www.bing.com/th?id=OHR.AutumnMerganser_JA-JP4454078554_1366x768.jpg",
      "size": "1366x768"
    },
    {
      "resolution": "FullHD",
      "url": "https://www.bing.com/th?id=OHR.AutumnMerganser_JA-JP4454078554_1920x1080.jpg",
      "size": "1920x1080"
    },
    {
      "resolution": "HD",
      "url": "https://www.bing.com/th?id=OHR.AutumnMerganser_JA-JP4454078554_1920x1200.jpg",
      "size": "1920x1200"
    },
    {
      "resolution": "UHD4K",
      "url": "https://www.bing.com/th?id=OHR.AutumnMerganser_JA-JP4454078554_UHD.jpg",
      "size": "3840x2160"
    }
  ],
  "timeInfo": {
    "startDate": "20251117",
    "fullStartDateTime": "202511171500",
    "endDate": "20251118"
  },
  "createdAt": "202511180228",
  "originalUrlBase": "/th?id=OHR.AutumnMerganser_JA-JP4454078554"
}