{
  "date": "Feb 12, 2026",
  "country": "Australia",
  "marketCode": "en-AU",
  "title": "Info",
  "bsTitle": "Info",
  "caption": "Blue-footed booby, Galápagos Islands, Ecuador",
  "copyright": "Blue-footed booby, Galápagos Islands, Ecuador (© Karine Aigner/TANDEM Stills + Motion)",
  "copyrightOnly": "© Karine Aigner/TANDEM Stills + Motion",
  "copyrightLink": "/search?q=Blue+footed+booby&form=hpcapt&filters=HpDate%3a%2220260212_0800%22",
  "description": "When romance calls, this bird lifts one bright blue foot, then the other, like it's auditioning for a talent show with very strict colour rules. Not metaphorically. Literally. Meet the blue-footed booby. Widely associated with the Galápagos Islands, these seabirds range across the eastern tropical Pacific.",
  "quiz": "/search?q=Bing+homepage+quiz&filters=WQOskey:%22HPQuiz_20260212_DarwinBooby%22&FORM=HPQUIZ",
  "hash": "e0f5ddcd7304cabb7c94261a2b33ae4e",
  "imageResolutions": [
    {
      "resolution": "Standard",
      "url": "https://www.bing.com/th?id=OHR.DarwinBooby_ROW9751594098_1366x768.jpg",
      "size": "1366x768"
    },
    {
      "resolution": "FullHD",
      "url": "https://www.bing.com/th?id=OHR.DarwinBooby_ROW9751594098_1920x1080.jpg",
      "size": "1920x1080"
    },
    {
      "resolution": "HD",
      "url": "https://www.bing.com/th?id=OHR.DarwinBooby_ROW9751594098_1920x1200.jpg",
      "size": "1920x1200"
    },
    {
      "resolution": "UHD4K",
      "url": "https://www.bing.com/th?id=OHR.DarwinBooby_ROW9751594098_UHD.jpg",
      "size": "3840x2160"
    }
  ],
  "timeInfo": {
    "startDate": "20260212",
    "fullStartDateTime": "202602120800",
    "endDate": "20260213"
  },
  "createdAt": "202602130336",
  "originalUrlBase": "/th?id=OHR.DarwinBooby_ROW9751594098"
}