{
  "date": "",
  "country": "Brazil",
  "marketCode": "pt-BR",
  "title": "O mestre das represas",
  "bsTitle": "",
  "caption": "",
  "copyright": "Castor, Alemanha (© Andyworks/Getty Images)",
  "copyrightOnly": "",
  "copyrightLink": "/search?q=dia+internacional+do+castor&form=hpcapt&mkt=pt-br",
  "description": "",
  "quiz": "/search?q=Bing+homepage+quiz&filters=WQOskey:%22HPQuiz_20260407_BeaverPortrait%22&FORM=HPQUIZ",
  "hash": "0843877d7cbdd3c52f48850c322353cf",
  "imageResolutions": [
    {
      "resolution": "Standard",
      "url": "https://www.bing.com/th?id=OHR.BeaverPortrait_PT-BR0841777069_1366x768.jpg",
      "size": "1366x768"
    },
    {
      "resolution": "FullHD",
      "url": "https://www.bing.com/th?id=OHR.BeaverPortrait_PT-BR0841777069_1920x1080.jpg",
      "size": "1920x1080"
    },
    {
      "resolution": "HD",
      "url": "https://www.bing.com/th?id=OHR.BeaverPortrait_PT-BR0841777069_1920x1200.jpg",
      "size": "1920x1200"
    },
    {
      "resolution": "UHD4K",
      "url": "https://www.bing.com/th?id=OHR.BeaverPortrait_PT-BR0841777069_UHD.jpg",
      "size": "3840x2160"
    }
  ],
  "timeInfo": {
    "startDate": "20260407",
    "fullStartDateTime": "202604070300",
    "endDate": "20260408"
  },
  "createdAt": "202604070345",
  "originalUrlBase": "/th?id=OHR.BeaverPortrait_PT-BR0841777069"
}