{
  "date": "",
  "country": "China",
  "marketCode": "zh-CN",
  "title": "不仅仅是一声咿呀学语",
  "bsTitle": "",
  "caption": "",
  "copyright": "撒丁岛母驴和幼崽, 法国 (© Klein & Hubert/Nature Picture Library)",
  "copyrightOnly": "",
  "copyrightLink": "/search?q=%e9%a9%b4&form=hpcapt&mkt=zh-cn",
  "description": "",
  "quiz": "/search?q=Bing+homepage+quiz&filters=WQOskey:%22HPQuiz_20260507_SardinianDonkey%22&FORM=HPQUIZ",
  "hash": "70583bce665feeb764b442065dd9089e",
  "imageResolutions": [
    {
      "resolution": "Standard",
      "url": "https://www.bing.com/th?id=OHR.SardinianDonkey_ZH-CN0758031524_1366x768.jpg",
      "size": "1366x768"
    },
    {
      "resolution": "FullHD",
      "url": "https://www.bing.com/th?id=OHR.SardinianDonkey_ZH-CN0758031524_1920x1080.jpg",
      "size": "1920x1080"
    },
    {
      "resolution": "HD",
      "url": "https://www.bing.com/th?id=OHR.SardinianDonkey_ZH-CN0758031524_1920x1200.jpg",
      "size": "1920x1200"
    },
    {
      "resolution": "UHD4K",
      "url": "https://www.bing.com/th?id=OHR.SardinianDonkey_ZH-CN0758031524_UHD.jpg",
      "size": "3840x2160"
    }
  ],
  "timeInfo": {
    "startDate": "20260507",
    "fullStartDateTime": "202605071600",
    "endDate": "20260508"
  },
  "createdAt": "202605080412",
  "originalUrlBase": "/th?id=OHR.SardinianDonkey_ZH-CN0758031524"
}