{
  "date": "",
  "country": "Italy",
  "marketCode": "it-IT",
  "title": "Guardiano silenzioso",
  "bsTitle": "",
  "caption": "",
  "copyright": "Faro di Tŵr Mawr, isola di Llanddwyn, Anglesey, Galles (© Lukas Bischoff/Getty Images)",
  "copyrightOnly": "",
  "copyrightLink": "/search?q=Isola+di+Ynys+Llanddwyn&form=hpcapt",
  "description": "",
  "quiz": "/search?q=Bing+homepage+quiz&filters=WQOskey:%22HPQuiz_20260430_TwrMawrLighthouse2026%22&FORM=HPQUIZ",
  "hash": "25156647401cba91000a86e34325b37a",
  "imageResolutions": [
    {
      "resolution": "Standard",
      "url": "https://www.bing.com/th?id=OHR.TwrMawrLighthouse2026_IT-IT6995398128_1366x768.jpg",
      "size": "1366x768"
    },
    {
      "resolution": "FullHD",
      "url": "https://www.bing.com/th?id=OHR.TwrMawrLighthouse2026_IT-IT6995398128_1920x1080.jpg",
      "size": "1920x1080"
    },
    {
      "resolution": "HD",
      "url": "https://www.bing.com/th?id=OHR.TwrMawrLighthouse2026_IT-IT6995398128_1920x1200.jpg",
      "size": "1920x1200"
    },
    {
      "resolution": "UHD4K",
      "url": "https://www.bing.com/th?id=OHR.TwrMawrLighthouse2026_IT-IT6995398128_UHD.jpg",
      "size": "3840x2160"
    }
  ],
  "timeInfo": {
    "startDate": "20260430",
    "fullStartDateTime": "202604302200",
    "endDate": "20260501"
  },
  "createdAt": "202605010443",
  "originalUrlBase": "/th?id=OHR.TwrMawrLighthouse2026_IT-IT6995398128"
}